web_scraper/__init__.py
web_scraper/scraper.py
web_scraper_vyas_yogesh_v01-0.1.2.dist-info/licenses/LICENSE
web_scraper_vyas_yogesh_v01-0.1.2.dist-info/METADATA
web_scraper_vyas_yogesh_v01-0.1.2.dist-info/WHEEL
web_scraper_vyas_yogesh_v01-0.1.2.dist-info/entry_points.txt
web_scraper_vyas_yogesh_v01-0.1.2.dist-info/top_level.txt
web_scraper_vyas_yogesh_v01-0.1.2.dist-info/RECORD
