Metadata-Version: 2.4
Name: web-scraper-vyas-yogesh-v01
Version: 0.1.2
Summary: A Selenium-based web scraper to collect person info and general data.
Author-email: yogesh vyas <vyasyogesh517@gmail.com>
License-Expression: Apache-2.0
Classifier: Programming Language :: Python :: 3
Classifier: Operating System :: OS Independent
Classifier: Development Status :: 4 - Beta
Requires-Python: >=3.8
License-File: LICENSE
Requires-Dist: selenium
Requires-Dist: webdriver-manager
Requires-Dist: requests
Dynamic: license-file
